{
  "variants": {
    "active=false,facing=north,waterlogged=false": {
      "model": "tolkienmobs:block/block_key_stone"
    },
    "active=true,facing=north,waterlogged=false": {
      "model": "tolkienmobs:block/block_key_stone_active"
    },
    "active=false,facing=south,waterlogged=false": {
      "model": "tolkienmobs:block/block_key_stone",
      "y": 180
    },
    "active=true,facing=south,waterlogged=false": {
      "model": "tolkienmobs:block/block_key_stone_active",
      "y": 180
    },
    "active=false,facing=west,waterlogged=false": {
      "model": "tolkienmobs:block/block_key_stone",
      "y": 270
    },
    "active=true,facing=west,waterlogged=false": {
      "model": "tolkienmobs:block/block_key_stone_active",
      "y": 270
    },
    "active=false,facing=east,waterlogged=false": {
      "model": "tolkienmobs:block/block_key_stone",
      "y": 90
    },
    "active=true,facing=east,waterlogged=false": {
      "model": "tolkienmobs:block/block_key_stone_active",
      "y": 90
    },
    "active=false,facing=north,waterlogged=true": {
      "model": "tolkienmobs:block/block_key_stone"
    },
    "active=true,facing=north,waterlogged=true": {
      "model": "tolkienmobs:block/block_key_stone_active"
    },
    "active=false,facing=south,waterlogged=true": {
      "model": "tolkienmobs:block/block_key_stone",
      "y": 180
    },
    "active=true,facing=south,waterlogged=true": {
      "model": "tolkienmobs:block/block_key_stone_active",
      "y": 180
    },
    "active=false,facing=west,waterlogged=true": {
      "model": "tolkienmobs:block/block_key_stone",
      "y": 270
    },
    "active=true,facing=west,waterlogged=true": {
      "model": "tolkienmobs:block/block_key_stone_active",
      "y": 270
    },
    "active=false,facing=east,waterlogged=true": {
      "model": "tolkienmobs:block/block_key_stone",
      "y": 90
    },
    "active=true,facing=east,waterlogged=true": {
      "model": "tolkienmobs:block/block_key_stone_active",
      "y": 90
    }
  }
}